tests/test_hello.py
vic_pkg/__init__.py
vic_pkg/dev.ini
vic_pkg/hello.py
my_vic_009-1.0.dist-info/LICENSE
my_vic_009-1.0.dist-info/METADATA
my_vic_009-1.0.dist-info/WHEEL
my_vic_009-1.0.dist-info/top_level.txt
my_vic_009-1.0.dist-info/RECORD
