Metadata-Version: 2.1
Name: my-vic-009
Version: 1.0
Summary: 学习打包
Home-page: https://www.vic.com
Author: vic
Author-email: vic@163.com
License: UNKNOWN
Platform: UNKNOWN
